kodiRename/__init__.py
kodiRename/_version.py
kodiRename/kodiRename.py
kodiRename/py.typed
kodi_rename-0.0.4.dist-info/licenses/LICENSE
kodi_rename-0.0.4.dist-info/METADATA
kodi_rename-0.0.4.dist-info/WHEEL
kodi_rename-0.0.4.dist-info/entry_points.txt
kodi_rename-0.0.4.dist-info/top_level.txt
kodi_rename-0.0.4.dist-info/RECORD
